aic/__init__.py
aic/agent.schema.json
tests/__init__.py
tests/test_aic.py
ai_characters-1.6.0.dist-info/LICENSE
ai_characters-1.6.0.dist-info/METADATA
ai_characters-1.6.0.dist-info/WHEEL
ai_characters-1.6.0.dist-info/top_level.txt
ai_characters-1.6.0.dist-info/RECORD
