Metadata-Version: 2.1
Name: ai_characters
Version: 1.6.0
Summary: Client for AI Characters
Author: Viacheslav Kovalevskyi
Author-email: viacheslav@kovalevskyi.com
License: MIT
License-File: LICENSE
Requires-Dist: google-cloud-storage ==2.16
Requires-Dist: jsonschema ==4.21
Requires-Dist: aic-tools ==1.0.0
Requires-Dist: aic-tools-fs ==0.0.1
Requires-Dist: crewai ==0.22
